devaiflow-1.0.1.data/data/DAF_AGENTS.md
devaiflow-1.0.1.dist-info/licenses/LICENSE
devflow/__init__.py
devflow/exceptions.py
devflow/agent/__init__.py
devflow/agent/claude_agent.py
devflow/agent/cursor_agent.py
devflow/agent/factory.py
devflow/agent/github_copilot_agent.py
devflow/agent/interface.py
devflow/agent/windsurf_agent.py
devflow/archive/__init__.py
devflow/archive/base.py
devflow/backup/__init__.py
devflow/backup/manager.py
devflow/cli/__init__.py
devflow/cli/completion.py
devflow/cli/main.py
devflow/cli/utils.py
devflow/cli/commands/__init__.py
devflow/cli/commands/active_command.py
devflow/cli/commands/backup_command.py
devflow/cli/commands/check_command.py
devflow/cli/commands/cleanup_command.py
devflow/cli/commands/cleanup_sessions_command.py
devflow/cli/commands/complete_command.py
devflow/cli/commands/context_commands.py
devflow/cli/commands/delete_command.py
devflow/cli/commands/discover_command.py
devflow/cli/commands/export_command.py
devflow/cli/commands/export_md_command.py
devflow/cli/commands/import_command.py
devflow/cli/commands/import_session_command.py
devflow/cli/commands/info_command.py
devflow/cli/commands/investigate_command.py
devflow/cli/commands/jira_add_comment_command.py
devflow/cli/commands/jira_create_commands.py
devflow/cli/commands/jira_create_dynamic.py
devflow/cli/commands/jira_new_command.py
devflow/cli/commands/jira_open_command.py
devflow/cli/commands/jira_update_command.py
devflow/cli/commands/jira_update_dynamic.py
devflow/cli/commands/jira_update_simple.py
devflow/cli/commands/jira_view_command.py
devflow/cli/commands/link_command.py
devflow/cli/commands/list_command.py
devflow/cli/commands/new_command.py
devflow/cli/commands/note_command.py
devflow/cli/commands/open_command.py
devflow/cli/commands/pause_command.py
devflow/cli/commands/release_command.py
devflow/cli/commands/repair_conversation_command.py
devflow/cli/commands/restore_command.py
devflow/cli/commands/resume_command.py
devflow/cli/commands/search_command.py
devaiflow-1.0.1.dist-info/METADATA
devaiflow-1.0.1.dist-info/WHEEL
devaiflow-1.0.1.dist-info/entry_points.txt
devaiflow-1.0.1.dist-info/top_level.txt
devaiflow-1.0.1.dist-info/RECORD
