Metadata-Version: 2.4
Name: devaiflow
Version: 1.0.1
Summary: DevAIFlow - Manage AI coding assistant sessions with optional issue tracker integration
Home-page: https://github.com/itdove/devaiflow
Author: Dominique Vernier
Project-URL: Bug Tracker, https://github.com/itdove/devaiflow/issues
Project-URL: Documentation, https://github.com/itdove/devaiflow/blob/main/README.md
Project-URL: Source Code, https://github.com/itdove/devaiflow
Project-URL: Logo, https://raw.githubusercontent.com/itdove/devaiflow/main/images/daf-logo-160x160.png
Keywords: ai,claude,github-copilot,cursor,windsurf,development-workflow,jira,project-management,automation,session-manager,devops,cli,ai-assistant
Classifier: Development Status :: 3 - Alpha
Classifier: Intended Audience :: Developers
Classifier: License :: OSI Approved :: Apache Software License
Classifier: Programming Language :: Python :: 3
Classifier: Programming Language :: Python :: 3.10
Classifier: Programming Language :: Python :: 3.11
Classifier: Programming Language :: Python :: 3.12
Requires-Python: >=3.10
License-File: LICENSE
Requires-Dist: click>=8.1.7
Requires-Dist: pydantic>=2.5.0
Requires-Dist: rich>=13.7.0
Requires-Dist: textual>=0.47.0
Requires-Dist: anthropic>=0.40.0
Requires-Dist: requests>=2.31.0
Requires-Dist: pyyaml>=6.0
Provides-Extra: dev
Requires-Dist: pytest>=7.4.3; extra == "dev"
Requires-Dist: pytest-cov>=4.1.0; extra == "dev"
Requires-Dist: black>=23.12.1; extra == "dev"
Requires-Dist: ruff>=0.1.9; extra == "dev"
Requires-Dist: mypy>=1.8.0; extra == "dev"
Dynamic: author
Dynamic: classifier
Dynamic: description
Dynamic: description-content-type
Dynamic: home-page
Dynamic: keywords
Dynamic: license-file
Dynamic: project-url
Dynamic: provides-extra
Dynamic: requires-dist
Dynamic: requires-python
Dynamic: summary
